Metadata-Version: 2.1
Name: jsonsubschema
Version: 0.0.7
Summary: A tool to check whether a JSON schema is subset/subschema of another JSON schema
Home-page: https://github.com/IBM/jsonsubschema
Author: Andrew Habib, Avraham Shinnar, Martin Hirzel
Author-email: andrew.a.habib@gmail.com
License: Apache License 2.0
Platform: UNKNOWN
